starlineage/__init__.py
starlineage/cli.py
starlineage/config.py
starlineage/drawing.py
starlineage/exceptions.py
starlineage/io.py
starlineage/runner.py
starlineage/build/asset-manifest.json
starlineage/build/editor.worker.js
starlineage/build/editor.worker.js.map
starlineage/build/favicon.ico
starlineage/build/index.html
starlineage/build/logo192.png
starlineage/build/logo512.png
starlineage/build/manifest.json
starlineage/build/robots.txt
starlineage/build/static/css/main.84d1d546.css
starlineage/build/static/css/main.84d1d546.css.map
starlineage/build/static/js/333.e647c004.chunk.js
starlineage/build/static/js/333.e647c004.chunk.js.map
starlineage/build/static/js/main.668062f8.js
starlineage/build/static/js/main.668062f8.js.LICENSE.txt
starlineage/build/static/js/main.668062f8.js.map
starlineage/build/static/media/codicon.4168b9c11e5075e9cfe6.ttf
starlineage/core/__init__.py
starlineage/core/analyzer.py
starlineage/core/holders.py
starlineage/core/metadata_provider.py
starlineage/core/models.py
starlineage/core/metadata/__init__.py
starlineage/core/metadata/dummy.py
starlineage/core/metadata/sqlalchemy.py
starlineage/core/parser/__init__.py
starlineage/core/parser/sqlfluff/__init__.py
starlineage/core/parser/sqlfluff/analyzer.py
starlineage/core/parser/sqlfluff/models.py
starlineage/core/parser/sqlfluff/utils.py
starlineage/core/parser/sqlfluff/extractors/__init__.py
starlineage/core/parser/sqlfluff/extractors/base.py
starlineage/core/parser/sqlfluff/extractors/copy.py
starlineage/core/parser/sqlfluff/extractors/create_insert.py
starlineage/core/parser/sqlfluff/extractors/cte.py
starlineage/core/parser/sqlfluff/extractors/drop.py
starlineage/core/parser/sqlfluff/extractors/merge.py
starlineage/core/parser/sqlfluff/extractors/noop.py
starlineage/core/parser/sqlfluff/extractors/rename.py
starlineage/core/parser/sqlfluff/extractors/select.py
starlineage/core/parser/sqlfluff/extractors/update.py
starlineage/core/parser/sqlparse/__init__.py
starlineage-1.0.6.dist-info/LICENSE
starlineage-1.0.6.dist-info/METADATA
starlineage-1.0.6.dist-info/WHEEL
starlineage-1.0.6.dist-info/entry_points.txt
starlineage-1.0.6.dist-info/top_level.txt
starlineage-1.0.6.dist-info/RECORD
